{"format":2,"version":"7.2.7","globals":"fdfd0fb9cac86f6bd55b132a994cbf47","files":{"d_7005a4ce5d73f943___init___py":{"hash":"e0aa4c97e4bca33bb6ea98641515e31f","index":{"nums":[0,1,2,0,0,0,0,0],"html_filename":"d_7005a4ce5d73f943___init___py.html","relative_filename":"src/hatch_ci/__init__.py"}},"d_7005a4ce5d73f943_cli_py":{"hash":"6434bcdee8d64d6b0c51317462cce110","index":{"nums":[0,1,72,0,72,18,0,18],"html_filename":"d_7005a4ce5d73f943_cli_py.html","relative_filename":"src/hatch_ci/cli.py"}},"d_7005a4ce5d73f943_common_py":{"hash":"3f1c2e747e86fae3744447395f472601","index":{"nums":[0,1,1,0,1,0,0,0],"html_filename":"d_7005a4ce5d73f943_common_py.html","relative_filename":"src/hatch_ci/common.py"}},"d_7005a4ce5d73f943_hooks_py":{"hash":"49a286f297620061a6d98a35f14981ba","index":{"nums":[0,1,5,0,5,0,0,0],"html_filename":"d_7005a4ce5d73f943_hooks_py.html","relative_filename":"src/hatch_ci/hooks.py"}},"d_7005a4ce5d73f943_scm_py":{"hash":"09485baef443027d4b5d7014a9e7d1aa","index":{"nums":[0,1,162,0,27,52,8,12],"html_filename":"d_7005a4ce5d73f943_scm_py.html","relative_filename":"src/hatch_ci/scm.py"}},"d_7005a4ce5d73f943_script_py":{"hash":"1f1f9597ce7c541f1fe029e8c67db0ee","index":{"nums":[0,1,67,2,67,20,0,20],"html_filename":"d_7005a4ce5d73f943_script_py.html","relative_filename":"src/hatch_ci/script.py"}},"d_7005a4ce5d73f943_tools_py":{"hash":"920e588d8d5656224648cba4f71d8359","index":{"nums":[0,1,201,0,10,84,8,12],"html_filename":"d_7005a4ce5d73f943_tools_py.html","relative_filename":"src/hatch_ci/tools.py"}},"d_7005a4ce5d73f943_version_hook_py":{"hash":"d8574928e09ee770fc8c01204295b58e","index":{"nums":[0,1,40,0,40,14,0,14],"html_filename":"d_7005a4ce5d73f943_version_hook_py.html","relative_filename":"src/hatch_ci/version_hook.py"}}}}