{
  "$schema": "../../block-class.schema.json",
  "$id": "https://collimator.ai/models/blocks/base/signal_routing/bus_creator.json",
  "base": {
    "name": "BusCreator",
    "namespace": "core",
    "description": "Create a bus signal from all of the inputs.",
    "feature_level": "dev",
    "supports_models": true,
    "supports_submodels": true,
    "supports_experiments": true
  },
  "modes": {
    "time": "agnostic"
  },
  "ports": {
    "has_automatic_ports": true,
    "outputs": {
      "static": [
        {
          "name": "out_0"
        }
      ]
    }
  },
  "parameter_definitions": [
    {
      "name": "bus_interface",
      "description": "The interface to create a bus out of",
      "data_type": "string",
      "default_value": ""
    }
  ]
}
